snifftools/__init__.py
snifftools/snifftools.py
snifftools-0.0.5.dist-info/LICENSE
snifftools-0.0.5.dist-info/METADATA
snifftools-0.0.5.dist-info/WHEEL
snifftools-0.0.5.dist-info/top_level.txt
snifftools-0.0.5.dist-info/RECORD
