Metadata-Version: 2.1
Name: snifftools
Version: 0.0.5
Summary: A small and simple library for simple python tasks
Home-page: https://github.com/sniff122/snifftools
Author: Lewis sniff122 Foster
Author-email: sniff122@sniff122.ga
License: UNKNOWN
Platform: UNKNOWN
Classifier: Programming Language :: Python :: 3
Classifier: License :: OSI Approved :: MIT License
Classifier: Operating System :: OS Independent
